datasette_ephemeral_tables/__init__.py
datasette_ephemeral_tables-0.2.3.dist-info/licenses/LICENSE
datasette_ephemeral_tables-0.2.3.dist-info/METADATA
datasette_ephemeral_tables-0.2.3.dist-info/WHEEL
datasette_ephemeral_tables-0.2.3.dist-info/entry_points.txt
datasette_ephemeral_tables-0.2.3.dist-info/top_level.txt
datasette_ephemeral_tables-0.2.3.dist-info/RECORD
