Metadata-Version: 2.4
Name: datasette-ephemeral-tables
Version: 0.2.3
Summary: Provide tables that expire after a time limit
Author: Simon Willison
License-Expression: Apache-2.0
Project-URL: Homepage, https://github.com/simonw/datasette-ephemeral-tables
Project-URL: Changelog, https://github.com/simonw/datasette-ephemeral-tables/releases
Project-URL: Issues, https://github.com/simonw/datasette-ephemeral-tables/issues
Project-URL: CI, https://github.com/simonw/datasette-ephemeral-tables/actions
Classifier: Framework :: Datasette
Requires-Python: >=3.10
License-File: LICENSE
Requires-Dist: datasette
Provides-Extra: test
Requires-Dist: pytest; extra == "test"
Requires-Dist: pytest-asyncio; extra == "test"
Dynamic: license-file
